{
    "connections": [
	{
	"src":{
		"port":"ReactionsMap",
		"process":"Assembly"
	},
	"tgt":{
		"port": "ReactionsMap",
		"process":"Transformation1"
	}
	},

	
	
	],
    "processes": {
        "Assembly": {
            "component": "AutoAssembly2"
        },
		 "Transformation1": {
            "component": "TransformationRefactored"
        },
		"TransformationControl1": {
            "component": "TransformationCotrans"
        },
		"TransformationControl2": {
            "component": "TransformationCotrans"
        },
		"TransformationControl3": {
            "component": "TransformationCotrans"
        },
		"TransformationControl4": {
            "component": "TransformationCotrans"
        },
		"TransformationControl5": {
            "component": "TransformationCotrans"
        },
		"TransformationControl6": {
            "component": "TransformationCotrans"
        }
    }
}
